[
    {
        "id": "f6f2187d.f17ca8",
        "type": "tab",
        "label": "SmartHome IoT",
        "disabled": false,
        "info": "Flujo de control y monitoreo para SmartHome IoT"
    },
    {
        "id": "mqtt_broker_config",
        "type": "mqtt-broker",
        "name": "Mosquitto Local",
        "broker": "mosquitto",
        "port": "1883",
        "clientid": "nodered-smarthome",
        "autoConnect": true,
        "usetls": false,
        "compatmode": false,
        "protocolVersion": "4",
        "keepalive": "60",
        "cleansession": true,
        "birthTopic": "smarthome/nodered/status",
        "birthQos": "0",
        "birthPayload": "online",
        "closeTopic": "smarthome/nodered/status",
        "closeQos": "0",
        "closePayload": "offline",
        "willTopic": "smarthome/nodered/status",
        "willQos": "0",
        "willPayload": "offline"
    },
    {
        "id": "telegram_bot_config",
        "type": "telegram bot",
        "botname": "SmartHomeBot",
        "usernames": "",
        "chatids": "",
        "baseapiurl": "",
        "testenvironment": false,
        "updatemode": "polling",
        "pollinterval": "1",
        "usesocks": false,
        "sockshost": "",
        "socksport": "",
        "socksusername": "",
        "sockspassword": "",
        "bothost": "",
        "botpath": "",
        "localbothost": "",
        "localbotport": "",
        "publicbotport": "",
        "privatekey": "",
        "certificate": "",
        "useselfsignedcertificate": false,
        "sslterminated": false,
        "verboselogging": false
    },
    {
        "id": "ui_tab_main",
        "type": "ui_tab",
        "name": "SmartHome Dashboard",
        "icon": "dashboard",
        "order": 1,
        "disabled": false,
        "hidden": false
    },
    {
        "id": "ui_group_sensors",
        "type": "ui_group",
        "name": "Sensores en Tiempo Real",
        "tab": "ui_tab_main",
        "order": 1,
        "disp": true,
        "width": "6",
        "collapse": false
    },
    {
        "id": "ui_group_control",
        "type": "ui_group",
        "name": "Control Manual y Actuadores",
        "tab": "ui_tab_main",
        "order": 2,
        "disp": true,
        "width": "6",
        "collapse": false
    },
    {
        "id": "ui_group_security",
        "type": "ui_group",
        "name": "Seguridad y Cámara (ESP32-CAM)",
        "tab": "ui_tab_main",
        "order": 3,
        "disp": true,
        "width": "6",
        "collapse": false
    },
    {
        "id": "ui_group_charts",
        "type": "ui_group",
        "name": "Historial de Temperatura",
        "tab": "ui_tab_main",
        "order": 4,
        "disp": true,
        "width": "6",
        "collapse": false
    },
    {
        "id": "96bd3462926bd100",
        "type": "ui_base",
        "theme": {
            "name": "theme-light",
            "lightTheme": {
                "default": "#0094CE",
                "baseColor": "#0094CE",
                "baseFont": "-apple-system,BlinkMacSystemFont,Segoe UI,Roboto,Oxygen-Sans,Ubuntu,Cantarell,Helvetica Neue,sans-serif",
                "edited": false
            },
            "darkTheme": {
                "default": "#097479",
                "baseColor": "#097479",
                "baseFont": "-apple-system,BlinkMacSystemFont,Segoe UI,Roboto,Oxygen-Sans,Ubuntu,Cantarell,Helvetica Neue,sans-serif",
                "edited": false
            },
            "customTheme": {
                "name": "Untitled Theme 1",
                "default": "#4B7930",
                "baseColor": "#4B7930",
                "baseFont": "-apple-system,BlinkMacSystemFont,Segoe UI,Roboto,Oxygen-Sans,Ubuntu,Cantarell,Helvetica Neue,sans-serif"
            },
            "themeState": {
                "base-color": {
                    "default": "#0094CE",
                    "value": "#0094CE",
                    "edited": false
                },
                "page-titlebar-backgroundColor": {
                    "value": "#0094CE",
                    "edited": false
                },
                "page-backgroundColor": {
                    "value": "#fafafa",
                    "edited": false
                },
                "page-sidebar-backgroundColor": {
                    "value": "#ffffff",
                    "edited": false
                },
                "group-textColor": {
                    "value": "#1bbfff",
                    "edited": false
                },
                "group-borderColor": {
                    "value": "#ffffff",
                    "edited": false
                },
                "group-backgroundColor": {
                    "value": "#ffffff",
                    "edited": false
                },
                "widget-textColor": {
                    "value": "#111111",
                    "edited": false
                },
                "widget-backgroundColor": {
                    "value": "#0094ce",
                    "edited": false
                },
                "widget-borderColor": {
                    "value": "#ffffff",
                    "edited": false
                },
                "base-font": {
                    "value": "-apple-system,BlinkMacSystemFont,Segoe UI,Roboto,Oxygen-Sans,Ubuntu,Cantarell,Helvetica Neue,sans-serif"
                }
            },
            "angularTheme": {
                "primary": "indigo",
                "accents": "blue",
                "warn": "red",
                "background": "grey",
                "palette": "light"
            }
        },
        "site": {
            "name": "Node-RED Dashboard",
            "hideToolbar": "false",
            "allowSwipe": "false",
            "lockMenu": "false",
            "allowTempTheme": "true",
            "dateFormat": "DD/MM/YYYY",
            "sizes": {
                "sx": 48,
                "sy": 48,
                "gx": 6,
                "gy": 6,
                "cx": 6,
                "cy": 6,
                "px": 0,
                "py": 0
            }
        }
    },
    {
        "id": "mqtt_in_datos",
        "type": "mqtt in",
        "z": "f6f2187d.f17ca8",
        "name": "Suscribir a Datos JSON",
        "topic": "smarthome/+/datos",
        "qos": "0",
        "datatype": "json",
        "broker": "mqtt_broker_config",
        "nl": false,
        "rap": true,
        "rh": 0,
        "inputs": 0,
        "x": 140,
        "y": 160,
        "wires": [
            [
                "parse_sensor_data",
                "csv_logging_trigger",
                "rules_evaluator",
                "sound_trigger"
            ]
        ]
    },
    {
        "id": "parse_sensor_data",
        "type": "function",
        "z": "f6f2187d.f17ca8",
        "name": "Extraer Variables",
        "func": "var temp = msg.payload.temperatura;\nvar hum = msg.payload.humedad;\nvar gas = msg.payload.gas;\nvar sound = msg.payload.sensor_extra;\n\nglobal.set(\"last_temp\", temp);\nglobal.set(\"last_hum\", hum);\nglobal.set(\"last_gas\", gas);\nglobal.set(\"last_sound\", sound);\n\nreturn [\n    { payload: temp, topic: \"temp\" },\n    { payload: hum, topic: \"hum\" },\n    { payload: gas, topic: \"gas\" },\n    { payload: sound, topic: \"sound\" }\n];",
        "outputs": 4,
        "noerr": 0,
        "initialize": "",
        "finalize": "",
        "libs": [],
        "x": 360,
        "y": 160,
        "wires": [
            [
                "ui_gauge_temp",
                "ui_chart_temp"
            ],
            [
                "ui_gauge_hum"
            ],
            [
                "ui_gauge_gas"
            ],
            [
                "ui_text_sound"
            ]
        ]
    },
    {
        "id": "ui_gauge_temp",
        "type": "ui_gauge",
        "z": "f6f2187d.f17ca8",
        "name": "Temperatura",
        "group": "ui_group_sensors",
        "order": 1,
        "width": 3,
        "height": 3,
        "gtype": "gage",
        "title": "Temperatura",
        "label": "°C",
        "format": "{{value}}",
        "min": 0,
        "max": "50",
        "colors": [
            "#00b500",
            "#e6e600",
            "#ca3838"
        ],
        "seg1": "28",
        "seg2": "35",
        "diff": false,
        "className": "",
        "x": 630,
        "y": 100,
        "wires": []
    },
    {
        "id": "ui_gauge_hum",
        "type": "ui_gauge",
        "z": "f6f2187d.f17ca8",
        "name": "Humedad",
        "group": "ui_group_sensors",
        "order": 2,
        "width": 3,
        "height": 3,
        "gtype": "gage",
        "title": "Humedad",
        "label": "%",
        "format": "{{value}}",
        "min": 0,
        "max": "100",
        "colors": [
            "#3399ff",
            "#00b500",
            "#e6e600"
        ],
        "seg1": "30",
        "seg2": "70",
        "diff": false,
        "className": "",
        "x": 620,
        "y": 160,
        "wires": []
    },
    {
        "id": "ui_gauge_gas",
        "type": "ui_gauge",
        "z": "f6f2187d.f17ca8",
        "name": "Nivel de Gas",
        "group": "ui_group_sensors",
        "order": 3,
        "width": 6,
        "height": 3,
        "gtype": "compass",
        "title": "Gas (MQ-2)",
        "label": "ppm",
        "format": "{{value}}",
        "min": 0,
        "max": "1024",
        "colors": [
            "#00b500",
            "#e6e600",
            "#ca3838"
        ],
        "seg1": "300",
        "seg2": "600",
        "diff": false,
        "className": "",
        "x": 630,
        "y": 220,
        "wires": []
    },
    {
        "id": "ui_text_sound",
        "type": "ui_text",
        "z": "f6f2187d.f17ca8",
        "group": "ui_group_sensors",
        "order": 4,
        "width": 6,
        "height": 1,
        "name": "Sonido",
        "label": "Sonido (MAX4466):",
        "format": "{{msg.payload}}",
        "layout": "row-spread",
        "className": "",
        "x": 610,
        "y": 280,
        "wires": []
    },
    {
        "id": "ui_chart_temp",
        "type": "ui_chart",
        "z": "f6f2187d.f17ca8",
        "name": "Gráfico de Temp",
        "group": "ui_group_charts",
        "order": 1,
        "width": 6,
        "height": 4,
        "label": "Temperatura Reciente",
        "chartType": "line",
        "legend": "false",
        "xformat": "HH:mm:ss",
        "interpolate": "linear",
        "nodata": "Esperando lecturas...",
        "dot": false,
        "ymin": "15",
        "ymax": "40",
        "removeOlder": 5,
        "removeOlderPoints": "",
        "removeOlderUnit": "m",
        "cutout": 0,
        "useOneColor": false,
        "useUTC": false,
        "colors": [
            "#ff7f0e",
            "#aec7e8",
            "#ff7f0e",
            "#ffbb78",
            "#2ca02c",
            "#98df8a",
            "#d62728",
            "#ff9896",
            "#9467bd"
        ],
        "outputs": 1,
        "useDifferentColor": false,
        "className": "",
        "x": 840,
        "y": 100,
        "wires": [
            []
        ]
    },
    {
        "id": "ui_switch_led",
        "type": "ui_switch",
        "z": "f6f2187d.f17ca8",
        "name": "Control LED",
        "label": "LED de Alerta",
        "tooltip": "Activar LED manual",
        "group": "ui_group_control",
        "order": 1,
        "width": 6,
        "height": 1,
        "passthru": true,
        "decouple": "false",
        "topic": "control/led",
        "style": "",
        "onvalue": "ON",
        "onvalueType": "str",
        "onicon": "",
        "oncolor": "",
        "offvalue": "OFF",
        "offvalueType": "str",
        "officon": "",
        "offcolor": "",
        "animate": true,
        "className": "",
        "x": 150,
        "y": 380,
        "wires": [
            [
                "mqtt_out_led"
            ]
        ]
    },
    {
        "id": "ui_switch_buzzer",
        "type": "ui_switch",
        "z": "f6f2187d.f17ca8",
        "name": "Control Buzzer",
        "label": "Zumbador (Buzzer)",
        "tooltip": "Activar Buzzer manual",
        "group": "ui_group_control",
        "order": 2,
        "width": 6,
        "height": 1,
        "passthru": true,
        "decouple": "false",
        "topic": "control/buzzer",
        "style": "",
        "onvalue": "ON",
        "onvalueType": "str",
        "onicon": "",
        "oncolor": "",
        "offvalue": "OFF",
        "offvalueType": "str",
        "officon": "",
        "offcolor": "",
        "animate": true,
        "className": "",
        "x": 160,
        "y": 440,
        "wires": [
            [
                "mqtt_out_buzzer"
            ]
        ]
    },
    {
        "id": "ui_button_capture",
        "type": "ui_button",
        "z": "f6f2187d.f17ca8",
        "name": "Capturar Imagen",
        "group": "ui_group_control",
        "order": 3,
        "width": 6,
        "height": 1,
        "passthru": false,
        "label": "Capturar Foto manual",
        "tooltip": "Mandar comando de captura a la cámara",
        "color": "",
        "bgcolor": "",
        "className": "",
        "icon": "camera_alt",
        "x": 160,
        "y": 520,
        "wires": [
            [
                "mqtt_out_camara_captura"
            ]
        ]
    },
    {
        "id": "mqtt_out_led",
        "type": "mqtt out",
        "z": "f6f2187d.f17ca8",
        "name": "Publicar control LED",
        "topic": "smarthome/equipo69/control/led",
        "qos": "0",
        "retain": "false",
        "respTopic": "",
        "contentType": "",
        "correl": "",
        "expiry": "",
        "broker": "mqtt_broker_config",
        "x": 420,
        "y": 380,
        "wires": []
    },
    {
        "id": "mqtt_out_buzzer",
        "type": "mqtt out",
        "z": "f6f2187d.f17ca8",
        "name": "Publicar control Buzzer",
        "topic": "smarthome/equipo69/control/buzzer",
        "qos": "0",
        "retain": "false",
        "respTopic": "",
        "contentType": "",
        "correl": "",
        "expiry": "",
        "broker": "mqtt_broker_config",
        "x": 430,
        "y": 440,
        "wires": []
    },
    {
        "id": "sound_trigger",
        "type": "function",
        "z": "f6f2187d.f17ca8",
        "name": "Trigger Sonido → Cámara",
        "func": "var threshold = context.get('sound_threshold') || 600;\nvar sound = msg.payload.sensor_extra;\nif (sound !== undefined && sound > threshold) {\n    return {\n        payload: {\"accion\":\"iniciar_burst\",\"duracion\":5},\n        topic: \"smarthome/equipo69/camara/captura\"\n    };\n}\nreturn null;",
        "outputs": 1,
        "timeout": "",
        "noerr": 0,
        "initialize": "context.set('sound_threshold', 600);",
        "finalize": "",
        "libs": [],
        "x": 190,
        "y": 320,
        "wires": [
            [
                "mqtt_out_camara_captura"
            ]
        ]
    },
    {
        "id": "mqtt_out_camara_captura",
        "type": "mqtt out",
        "z": "f6f2187d.f17ca8",
        "name": "Publicar camara/captura",
        "topic": "smarthome/equipo69/camara/captura",
        "qos": "0",
        "retain": "false",
        "respTopic": "",
        "contentType": "",
        "correl": "",
        "expiry": "",
        "broker": "mqtt_broker_config",
        "x": 430,
        "y": 520,
        "wires": []
    },
    {
        "id": "mqtt_in_camara_evento",
        "type": "mqtt in",
        "z": "f6f2187d.f17ca8",
        "name": "Presencia y Rostros",
        "topic": "smarthome/equipo69/camara/evento",
        "qos": "0",
        "datatype": "json",
        "broker": "mqtt_broker_config",
        "nl": false,
        "rap": true,
        "rh": 0,
        "inputs": 0,
        "x": 150,
        "y": 620,
        "wires": [
            [
                "process_vision_data"
            ]
        ]
    },
    {
        "id": "process_vision_data",
        "type": "function",
        "z": "f6f2187d.f17ca8",
        "name": "Procesar Visión",
        "func": "var human = msg.payload.human; // true / false\nvar faces = msg.payload.faces; // Array de nombres\n\nvar presenceText = human ? \"DETECTADO\" : \"Nadie en cámara\";\nvar facesText = (faces && faces.length > 0) ? faces.join(\", \") : \"Ninguno\";\n\nreturn [\n    { payload: presenceText },\n    { payload: facesText },\n    { payload: human ? \"#ff3333\" : \"#33cc33\" }\n];",
        "outputs": 3,
        "noerr": 0,
        "initialize": "",
        "finalize": "",
        "libs": [],
        "x": 380,
        "y": 620,
        "wires": [
            [
                "ui_text_presence"
            ],
            [
                "ui_text_faces"
            ],
            [
                "ui_status_indicator"
            ]
        ]
    },
    {
        "id": "ui_text_presence",
        "type": "ui_text",
        "z": "f6f2187d.f17ca8",
        "group": "ui_group_security",
        "order": 1,
        "width": 3,
        "height": 1,
        "name": "Presencia Humana",
        "label": "Humano:",
        "format": "{{msg.payload}}",
        "layout": "row-spread",
        "className": "",
        "x": 650,
        "y": 580,
        "wires": []
    },
    {
        "id": "ui_status_indicator",
        "type": "ui_template",
        "z": "f6f2187d.f17ca8",
        "group": "ui_group_security",
        "name": "Indicador Visual",
        "order": 2,
        "width": 3,
        "height": 1,
        "format": "<div style=\"display: flex; align-items: center; justify-content: flex-end; height: 100%; padding-right: 10px;\">\n    <div style=\"width: 15px; height: 15px; border-radius: 50%; background-color: {{msg.payload || '#33cc33'}}; box-shadow: 0 0 8px {{msg.payload || '#33cc33'}};\"></div>\n    <span style=\"margin-left: 8px; font-weight: bold; font-size: 13px;\">Estado</span>\n</div>",
        "storeOutMessages": true,
        "fwdInMessages": true,
        "className": "",
        "x": 640,
        "y": 660,
        "wires": [
            []
        ]
    },
    {
        "id": "ui_text_faces",
        "type": "ui_text",
        "z": "f6f2187d.f17ca8",
        "group": "ui_group_security",
        "order": 3,
        "width": 6,
        "height": 1,
        "name": "Rostros",
        "label": "Rostros:",
        "format": "{{msg.payload}}",
        "layout": "row-spread",
        "className": "",
        "x": 620,
        "y": 620,
        "wires": []
    },
    {
        "id": "ui_camera_feed",
        "type": "ui_template",
        "z": "f6f2187d.f17ca8",
        "group": "ui_group_security",
        "name": "Cámara (última captura)",
        "order": 4,
        "width": 6,
        "height": 6,
        "format": "<div style=\"text-align:center; height:100%; display:flex; flex-direction:column; justify-content:center; background:#1a1a1a; border-radius:6px; min-height:240px;\">\n    <div ng-if=\"!msg || !msg.payload\" style=\"color:#888; font-size:14px;\">Esperando captura...</div>\n    <div ng-bind-html=\"msg.payload\" style=\"width:100%;\"></div>\n</div>",
        "storeOutMessages": true,
        "fwdInMessages": true,
        "className": "",
        "x": 930,
        "y": 640,
        "wires": [
            []
        ]
    },
    {
        "id": "b64_conv.001abc",
        "type": "function",
        "z": "f6f2187d.f17ca8",
        "name": "JPEG a Base64",
        "func": "if (msg.payload && msg.payload.length > 0) {\n    var base64 = msg.payload.toString('base64');\n    msg.payload = '<img src=\"data:image/jpeg;base64,' + base64 + '\" style=\"width:100%; height:auto; border:2px solid #444; border-radius:4px; object-fit:contain;\" />';\n} else {\n    msg.payload = '<div style=\"color:#888;\">Imagen vacía</div>';\n}\nreturn msg;",
        "outputs": 1,
        "noerr": 0,
        "initialize": "",
        "finalize": "",
        "libs": [],
        "x": 900,
        "y": 480,
        "wires": [
            [
                "ui_camera_feed"
            ]
        ]
    },
    {
        "id": "img_in_001.abc",
        "type": "mqtt in",
        "z": "f6f2187d.f17ca8",
        "name": "Imagen Cámara",
        "topic": "smarthome/equipo69/camara/imagen",
        "qos": "0",
        "datatype": "buffer",
        "broker": "mqtt_broker_config",
        "nl": false,
        "rap": true,
        "rh": 0,
        "inputs": 0,
        "x": 880,
        "y": 380,
        "wires": [
            [
                "b64_conv.001abc"
            ]
        ]
    },
    {
        "id": "csv_logging_trigger",
        "type": "function",
        "z": "f6f2187d.f17ca8",
        "name": "Formato CSV",
        "func": "var temp = msg.payload.temperatura || \"\";\nvar hum = msg.payload.humedad || \"\";\nvar gas = msg.payload.gas || \"\";\nvar sound = msg.payload.sensor_extra || \"\";\nvar alert = msg.payload.alerta || \"NORMAL\";\nvar timestamp = new Date().toISOString();\n\nmsg.payload = timestamp + \",\" + temp + \",\" + hum + \",\" + gas + \",\" + sound + \",\" + alert;\nreturn msg;",
        "outputs": 1,
        "noerr": 0,
        "initialize": "",
        "finalize": "",
        "libs": [],
        "x": 380,
        "y": 240,
        "wires": [
            [
                "write_csv_file"
            ]
        ]
    },
    {
        "id": "write_csv_file",
        "type": "file",
        "z": "f6f2187d.f17ca8",
        "name": "Guardar en CSV",
        "filename": "/data/historial.csv",
        "filenameType": "str",
        "appendNewline": true,
        "createDir": true,
        "overwriteFile": "false",
        "encoding": "utf8",
        "x": 620,
        "y": 340,
        "wires": [
            []
        ]
    },
    {
        "id": "rules_evaluator",
        "type": "function",
        "z": "f6f2187d.f17ca8",
        "name": "Reglas de Control Automático",
        "func": "var temp = msg.payload.temperatura;\nvar gas = msg.payload.gas;\nvar gasThreshold = context.get('gas_threshold') || 1020;\nvar alertTriggered = false;\nvar alertMsg = \"\";\n\nif (temp && temp > 30) {\n    alertTriggered = true;\n    alertMsg += \"⚠️ ¡Temperatura crítica: \" + temp + \"°C!\\n\";\n}\n\nif (gas && gas > gasThreshold) {\n    alertTriggered = true;\n    alertMsg += \"🔥 ¡Alerta de Gas detectada: \" + gas + \" ppm!\\n\";\n}\n\nif (alertTriggered) {\n    var telegramMsg = {\n        payload: {\n            chatId: -1003906928304,\n            type: \"message\",\n            content: \"🚨 *[SmartHome ALERTA]*\\n\\n\" + alertMsg + \"\\n*Timestamp:* \" + new Date().toLocaleString()\n        }\n    };\n    \n    return [\n        { payload: \"ON\", topic: \"control/led\" },\n        { payload: \"ON\", topic: \"control/buzzer\" },\n        telegramMsg\n    ];\n} else {\n    return [\n        null,\n        null,\n        null\n    ];\n}",
        "outputs": 3,
        "timeout": "",
        "noerr": 0,
        "initialize": "context.set('gas_threshold', 1020);",
        "finalize": "",
        "libs": [],
        "x": 390,
        "y": 80,
        "wires": [
            [
                "mqtt_out_led"
            ],
            [
                "mqtt_out_buzzer"
            ],
            [
                "telegram_out"
            ]
        ]
    },
    {
        "id": "telegram_in",
        "type": "telegram receiver",
        "z": "f6f2187d.f17ca8",
        "name": "Comandos Telegram",
        "bot": "telegram_bot_config",
        "saveDataDir": "",
        "filterCommands": false,
        "hasinput": false,
        "inputs": 0,
        "handleallupdates": false,
        "handleprocessupdates": false,
        "x": 140,
        "y": 740,
        "wires": [
            [
                "telegram_router"
            ],
            []
        ]
    },
    {
        "id": "telegram_router",
        "type": "function",
        "z": "f6f2187d.f17ca8",
        "name": "Router de Comandos",
        "func": "var command = msg.payload.content || msg.payload.text;\nvar chatId = msg.payload.chatId || (msg.payload.chat && msg.payload.chat.id) || msg.chatId;\n\n// Debug de entrada en consola de Node-RED\nnode.log(\"Recibido comando: \" + command + \" de chatId: \" + chatId);\n\nif (command === \"/status\") {\n    var temp = global.get(\"last_temp\") || \"No disponible\";\n    var hum = global.get(\"last_hum\") || \"No disponible\";\n    var gas = global.get(\"last_gas\") || \"No disponible\";\n    var sound = global.get(\"last_sound\") || \"No disponible\";\n    \n    msg.payload = {\n        chatId: chatId,\n        type: \"message\",\n        content: \"📊 *SmartHome Status*\\n\\n\" +\n                 \"🌡️ *Temp:* \" + temp + \" °C\\n\" +\n                 \"💧 *Humedad:* \" + hum + \" %\\n\" +\n                 \"🔥 *Gas (MQ-2):* \" + gas + \" ppm\\n\" +\n                 \"🔊 *Sonido:* \" + sound + \"\\n\\n\" +\n                 \"*Timestamp:* \" + new Date().toLocaleString()\n    };\n    node.log(\"Respondiendo con status a: \" + chatId);\n    return [msg, null];\n} else if (command === \"/ayuda\" || command === \"/start\") {\n    msg.payload = {\n        chatId: chatId,\n        type: \"message\",\n        content: \"🤖 *SmartHome Bot*\\n\\n\" +\n                 \"Comandos disponibles:\\n\" +\n                 \"🔹 `/status` - Muestra lecturas en tiempo real\\n\" +\n                 \"🔹 `/ayuda` - Lista los comandos\"\n    };\n    node.log(\"Respondiendo con ayuda a: \" + chatId);\n    return [msg, null];\n}\nnode.log(\"Comando desconocido ignorado.\");\nreturn null;",
        "outputs": 2,
        "noerr": 0,
        "initialize": "",
        "finalize": "",
        "libs": [],
        "x": 390,
        "y": 740,
        "wires": [
            [
                "telegram_out",
                "debug_router_out"
            ],
            []
        ]
    },
    {
        "id": "telegram_out",
        "type": "telegram sender",
        "z": "f6f2187d.f17ca8",
        "name": "Enviar a Telegram",
        "bot": "telegram_bot_config",
        "haserroroutput": false,
        "outputs": 1,
        "x": 810,
        "y": 740,
        "wires": [
            []
        ]
    },
    {
        "id": "debug_router_out",
        "type": "debug",
        "z": "f6f2187d.f17ca8",
        "name": "Debug Router Salida",
        "active": true,
        "tosidebar": true,
        "console": true,
        "tostatus": false,
        "complete": "true",
        "targetType": "full",
        "statusVal": "",
        "statusType": "auto",
        "x": 670,
        "y": 800,
        "wires": []
    },
    {
        "id": "inject_telegram_test",
        "type": "inject",
        "z": "f6f2187d.f17ca8",
        "name": "Inyectar Alerta de Prueba",
        "props": [
            {
                "p": "payload",
                "v": "{\"chatId\":1511171371,\"type\":\"message\",\"content\":\"🔔 Prueba de inyección manual desde Node-RED\"}",
                "vt": "json"
            }
        ],
        "repeat": "",
        "crontab": "",
        "once": false,
        "onceDelay": 0.1,
        "topic": "",
        "x": 390,
        "y": 860,
        "wires": [
            [
                "telegram_out"
            ]
        ]
    }
]